mcp_image_zoom/__init__.py
mcp_image_zoom/server.py
mcp_image_zoom-0.1.1.dist-info/METADATA
mcp_image_zoom-0.1.1.dist-info/WHEEL
mcp_image_zoom-0.1.1.dist-info/entry_points.txt
mcp_image_zoom-0.1.1.dist-info/RECORD
