Metadata-Version: 2.4
Name: mcp-image-zoom
Version: 0.1.1
Summary: MCP server for image zoom-in tool, crop and resize image regions for detailed analysis
Project-URL: Homepage, https://github.com/your-username/mcp-image-zoom
Project-URL: Repository, https://github.com/your-username/mcp-image-zoom
Author-email: Your Name <your@email.com>
License-Expression: Apache-2.0
Keywords: crop,image,mcp,qwen,vision,zoom
Classifier: Development Status :: 3 - Alpha
Classifier: Intended Audience :: Developers
Classifier: License :: OSI Approved :: Apache Software License
Classifier: Programming Language :: Python :: 3
Classifier: Programming Language :: Python :: 3.10
Classifier: Programming Language :: Python :: 3.11
Classifier: Programming Language :: Python :: 3.12
Requires-Python: >=3.10
Requires-Dist: mcp>=1.0.0
Requires-Dist: pillow>=10.0.0
Requires-Dist: requests>=2.28.0
